segjb/__init__.py
segjb/newdict.dat
segjb/punctuations.dat
segjb/stopwords.dat
segjb-1.0.dist-info/METADATA
segjb-1.0.dist-info/RECORD
segjb-1.0.dist-info/WHEEL
segjb-1.0.dist-info/top_level.txt
