Metadata-Version: 2.1
Name: segjb
Version: 1.0
Summary: A wrapper for jieba segmentation
Home-page: https://github.com/kn45/SegJb
Author: Travis Chen
Author-email: teckiechen@gmail.com
License: MIT
Keywords: nlp,tokenizing,segmentation
Platform: UNKNOWN
Classifier: Natural Language :: Chinese (Simplified)
Classifier: Natural Language :: Chinese (Traditional)
Classifier: Programming Language :: Python :: 2.7
Classifier: Programming Language :: Python :: 3.6
Requires-Dist: jieba
